CL_Write_Results_Library/CL_Write_Results_Library.py
CL_Write_Results_Library/__init__.py
CL_Write_Results_Library-1.5.2.dist-info/LICENSE.txt
CL_Write_Results_Library-1.5.2.dist-info/METADATA
CL_Write_Results_Library-1.5.2.dist-info/WHEEL
CL_Write_Results_Library-1.5.2.dist-info/top_level.txt
CL_Write_Results_Library-1.5.2.dist-info/RECORD
