Metadata-Version: 2.1
Name: CL-Write-Results-Library
Version: 1.5.2
Summary: A custom Library
Home-page: http://10.21.37.110/corp_sieq/Partner%20Automation%20Testing%20Trial/_git/CL_Write_Results_Library
Author: sieqqc
Author-email: sieqqc@gmail.com
License: UNKNOWN
Platform: UNKNOWN
Classifier: Programming Language :: Python :: 3
Classifier: License :: OSI Approved :: MIT License
Classifier: Operating System :: OS Independent
Requires-Python: >=3.6
